{"name":"build-javascript","namedChunkGroups":{"polyfill":{"name":"polyfill","assets":[{"name":"webpack-runtime-1097c23f165f92de2b1b.js","size":3175},{"name":"polyfill-606811feb5fcd75925eb.js","size":85007}],"filteredAssets":0,"assetsSize":88182,"filteredAuxiliaryAssets":2,"auxiliaryAssetsSize":223951},"app":{"name":"app","assets":[{"name":"webpack-runtime-1097c23f165f92de2b1b.js","size":3175},{"name":"framework-197032f91f2776da843d.js","size":141378},{"name":"styles.019799b602a76f6d07f6.css","size":196205},{"name":"app-d53e73d76ad3664022eb.js","size":174965}],"filteredAssets":0,"assetsSize":515723,"filteredAuxiliaryAssets":3,"auxiliaryAssetsSize":1201486},"component---src-pages-index-tsx":{"name":"component---src-pages-index-tsx","assets":[{"name":"component---src-pages-index-tsx-ab8d5b3f064390e7a888.js","size":271078}],"filteredAssets":0,"assetsSize":271078,"filteredAuxiliaryAssets":1,"auxiliaryAssetsSize":799399}},"assetsByChunkName":{"polyfill":["webpack-runtime-1097c23f165f92de2b1b.js","polyfill-606811feb5fcd75925eb.js"],"app":["webpack-runtime-1097c23f165f92de2b1b.js","framework-197032f91f2776da843d.js","styles.019799b602a76f6d07f6.css","app-d53e73d76ad3664022eb.js"],"component---src-pages-index-tsx":["component---src-pages-index-tsx-ab8d5b3f064390e7a888.js"]},"childAssetsByChunkName":{}}